QtDesign6/QtdWidgets.py
QtDesign6/__init__.py
QtDesign6-0.0.1.dist-info/LICENSE
QtDesign6-0.0.1.dist-info/METADATA
QtDesign6-0.0.1.dist-info/WHEEL
QtDesign6-0.0.1.dist-info/top_level.txt
QtDesign6-0.0.1.dist-info/RECORD
